setup.py
spanner/__init__.py
spanner/countdown.py
spanner/decorators.py
spanner/system.py
spanner/tables.py
spanner.egg-info/PKG-INFO
spanner.egg-info/SOURCES.txt
spanner.egg-info/dependency_links.txt
spanner.egg-info/requires.txt
spanner.egg-info/top_level.txt
test/test_countdown.py
test/test_decorators.py
test/test_tables.py