Metadata-Version: 1.1
Name: spanner
Version: 1.0.2
Summary: An accumulation of utilities / convenience functions for python
Home-page: https://github.com/dbjohnson/python-utils
Author: Bryan Johnson
Author-email: d.bryan.johnson@gmail.com
License: UNKNOWN
Download-URL: https://github.com/dbjohnson/spanner/tarball/1.0.2
Platform: UNKNOWN
